{
  "schema_version": 1,
  "generated_at": "2026-06-19T15:13:44+00:00",
  "match_date": "2026-06-18",
  "scoring_version": "v0.3",
  "matches": [
    {
      "match_key": "FIFA-2026-M25-CZE-RSA",
      "match_no": 25,
      "match_date": "2026-06-18",
      "kickoff_time": "12:00",
      "stadium": "Atlanta Stadium",
      "home_team": "Czechia",
      "away_team": "South Africa",
      "home_score": 1,
      "away_score": 1
    },
    {
      "match_key": "FIFA-2026-M26-SUI-BIH",
      "match_no": 26,
      "match_date": "2026-06-18",
      "kickoff_time": "12:00",
      "stadium": "Los Angeles Stadium",
      "home_team": "Switzerland",
      "away_team": "Bosnia and Herzegovina",
      "home_score": 4,
      "away_score": 1
    },
    {
      "match_key": "FIFA-2026-M27-CAN-QAT",
      "match_no": 27,
      "match_date": "2026-06-18",
      "kickoff_time": "15:00",
      "stadium": "BC Place Vancouver",
      "home_team": "Canada",
      "away_team": "Qatar",
      "home_score": 6,
      "away_score": 0
    },
    {
      "match_key": "FIFA-2026-M28-MEX-KOR",
      "match_no": 28,
      "match_date": "2026-06-18",
      "kickoff_time": "19:00",
      "stadium": "Guadalajara Stadium",
      "home_team": "Mexico",
      "away_team": "Korea Republic",
      "home_score": 1,
      "away_score": 0
    }
  ],
  "choices": [
    {
      "award_type": "player_of_the_day",
      "award_label": {
        "en": "Player of the Day",
        "zh": "每日最佳球员"
      },
      "rank": 1,
      "match_key": "FIFA-2026-M27-CAN-QAT",
      "match_no": 27,
      "player_no": 10,
      "player_name": "Jonathan DAVID",
      "team": "Canada",
      "opponent": "Qatar",
      "home_score": 6,
      "away_score": 0,
      "team_final_goals": 6,
      "opponent_final_goals": 0,
      "position": "FW",
      "score": 112.5,
      "primary_score": "headline_score",
      "role_scores": {
        "attacking_threat": 47.55,
        "impact": 24.0,
        "progressor": 8.36,
        "off_ball": 32.9,
        "defensive": 6.45,
        "physical": 16.41
      },
      "progression_benchmark": {
        "score": 1.7,
        "quality": "thin",
        "support_actions": 0.0,
        "pass_only_line_break_volume": false
      },
      "hidden_gem_profile": {
        "eligible": false,
        "profile": "insufficient_evidence",
        "score": 32.9
      },
      "score_components": [
        {
          "metric": "goals",
          "value": 3,
          "weight": 8.0,
          "contribution": 24.0,
          "score": "attacking_threat"
        },
        {
          "metric": "offers_received",
          "value": 15,
          "weight": 1.0,
          "contribution": 15.0,
          "score": "off_ball"
        },
        {
          "metric": "on_target",
          "value": 6,
          "weight": 2.0,
          "contribution": 12.0,
          "score": "attacking_threat"
        },
        {
          "metric": "hat_trick",
          "value": 1,
          "weight": 12.0,
          "contribution": 12.0,
          "score": "impact"
        },
        {
          "metric": "total_distance_m",
          "value": 10188.9,
          "weight": 0.001,
          "contribution": 10.19,
          "score": "physical"
        },
        {
          "metric": "in_behind",
          "value": 15,
          "weight": 0.6,
          "contribution": 9.0,
          "score": "off_ball"
        }
      ],
      "evidence_chips": {
        "en": [
          "hat-trick",
          "high shot quality"
        ],
        "zh": [
          "帽子戏法",
          "射门质量突出"
        ]
      }
    },
    {
      "award_type": "player_of_the_day",
      "award_label": {
        "en": "Player of the Day",
        "zh": "每日最佳球员"
      },
      "rank": 2,
      "match_key": "FIFA-2026-M25-CZE-RSA",
      "match_no": 25,
      "player_no": 4,
      "player_name": "Teboho MOKOENA",
      "team": "South Africa",
      "opponent": "Czechia",
      "home_score": 1,
      "away_score": 1,
      "team_final_goals": 1,
      "opponent_final_goals": 1,
      "position": "MF",
      "score": 91.6,
      "primary_score": "headline_score",
      "role_scores": {
        "attacking_threat": 19.55,
        "impact": 5.0,
        "progressor": 61.32,
        "off_ball": 49.7,
        "defensive": 26.45,
        "physical": 16.78
      },
      "progression_benchmark": {
        "score": 24.3,
        "quality": "strong",
        "support_actions": 3.0,
        "pass_only_line_break_volume": false
      },
      "hidden_gem_profile": {
        "eligible": true,
        "profile": "progression_engine",
        "score": 24.3
      },
      "score_components": [
        {
          "metric": "line_breaks_completed",
          "value": 29,
          "weight": 2.0,
          "contribution": 58.0,
          "score": "progressor"
        },
        {
          "metric": "offers_received",
          "value": 38,
          "weight": 1.0,
          "contribution": 38.0,
          "score": "off_ball"
        },
        {
          "metric": "total_distance_m",
          "value": 10523.7,
          "weight": 0.001,
          "contribution": 10.52,
          "score": "physical"
        },
        {
          "metric": "goals",
          "value": 1,
          "weight": 8.0,
          "contribution": 8.0,
          "score": "attacking_threat"
        },
        {
          "metric": "possession_regains",
          "value": 6,
          "weight": 1.3,
          "contribution": 7.8,
          "score": "defensive"
        },
        {
          "metric": "offers_received",
          "value": 38,
          "weight": 0.2,
          "contribution": 7.6,
          "score": "attacking_threat"
        }
      ],
      "evidence_chips": {
        "en": [
          "equaliser",
          "goal scorer",
          "repeated line breaks",
          "found again and again"
        ],
        "zh": [
          "扳平进球",
          "取得进球",
          "持续打穿防线",
          "持续接应"
        ]
      }
    },
    {
      "award_type": "player_of_the_day",
      "award_label": {
        "en": "Player of the Day",
        "zh": "每日最佳球员"
      },
      "rank": 3,
      "match_key": "FIFA-2026-M26-SUI-BIH",
      "match_no": 26,
      "player_no": 9,
      "player_name": "Johan MANZAMBI",
      "team": "Switzerland",
      "opponent": "Bosnia and Herzegovina",
      "home_score": 4,
      "away_score": 1,
      "team_final_goals": 4,
      "opponent_final_goals": 1,
      "position": "MF",
      "score": 90.9,
      "primary_score": "headline_score",
      "role_scores": {
        "attacking_threat": 24.1,
        "impact": 32.0,
        "progressor": 7.2,
        "off_ball": 12.2,
        "defensive": 0.65,
        "physical": 8.74
      },
      "progression_benchmark": {
        "score": 8.1,
        "quality": "thin",
        "support_actions": 4.0,
        "pass_only_line_break_volume": false
      },
      "hidden_gem_profile": {
        "eligible": false,
        "profile": "insufficient_evidence",
        "score": 12.2
      },
      "score_components": [
        {
          "metric": "goals",
          "value": 2,
          "weight": 8.0,
          "contribution": 16.0,
          "score": "attacking_threat"
        },
        {
          "metric": "brace",
          "value": 1,
          "weight": 8.0,
          "contribution": 8.0,
          "score": "impact"
        },
        {
          "metric": "substitute_goal",
          "value": 2,
          "weight": 4.0,
          "contribution": 8.0,
          "score": "impact"
        },
        {
          "metric": "substitute_brace",
          "value": 1,
          "weight": 8.0,
          "contribution": 8.0,
          "score": "impact"
        },
        {
          "metric": "offers_received",
          "value": 7,
          "weight": 1.0,
          "contribution": 7.0,
          "score": "off_ball"
        },
        {
          "metric": "top_speed_kmh",
          "value": 29.6,
          "weight": 0.2,
          "contribution": 5.92,
          "score": "physical"
        }
      ],
      "evidence_chips": {
        "en": [
          "brace",
          "substitute brace",
          "opening goal"
        ],
        "zh": [
          "梅开二度",
          "替补双响",
          "首开纪录"
        ]
      }
    },
    {
      "award_type": "impact_pick",
      "award_label": {
        "en": "Impact Pick",
        "zh": "影响力精选"
      },
      "rank": 1,
      "match_key": "FIFA-2026-M28-MEX-KOR",
      "match_no": 28,
      "player_no": 7,
      "player_name": "Luis ROMO",
      "team": "Mexico",
      "opponent": "Korea Republic",
      "home_score": 1,
      "away_score": 0,
      "team_final_goals": 1,
      "opponent_final_goals": 0,
      "position": "MF",
      "score": 25.0,
      "primary_score": "impact",
      "role_scores": {
        "attacking_threat": 16.15,
        "impact": 25.0,
        "progressor": 14.64,
        "off_ball": 36.5,
        "defensive": 13.6,
        "physical": 14.86
      },
      "progression_benchmark": {
        "score": 7.75,
        "quality": "thin",
        "support_actions": 0.0,
        "pass_only_line_break_volume": false
      },
      "hidden_gem_profile": {
        "eligible": false,
        "profile": "insufficient_evidence",
        "score": 36.5
      },
      "score_components": [
        {
          "metric": "match_winning_goal",
          "value": 1,
          "weight": 12.0,
          "contribution": 12.0
        },
        {
          "metric": "only_goal_winner",
          "value": 1,
          "weight": 6.0,
          "contribution": 6.0
        },
        {
          "metric": "go_ahead_goal",
          "value": 1,
          "weight": 5.0,
          "contribution": 5.0
        },
        {
          "metric": "opening_goal",
          "value": 1,
          "weight": 2.0,
          "contribution": 2.0
        }
      ],
      "evidence_chips": {
        "en": [
          "only goal",
          "match-winning goal",
          "goal scorer",
          "between-line presence"
        ],
        "zh": [
          "全场唯一进球",
          "打入制胜球",
          "取得进球",
          "在防线之间活跃"
        ]
      }
    },
    {
      "award_type": "progression_pick",
      "award_label": {
        "en": "Progression Pick",
        "zh": "推进精选"
      },
      "rank": 1,
      "match_key": "FIFA-2026-M26-SUI-BIH",
      "match_no": 26,
      "player_no": 10,
      "player_name": "Granit XHAKA",
      "team": "Switzerland",
      "opponent": "Bosnia and Herzegovina",
      "home_score": 4,
      "away_score": 1,
      "team_final_goals": 4,
      "opponent_final_goals": 1,
      "position": "MF",
      "score": 66.9,
      "primary_score": "progressor",
      "role_scores": {
        "attacking_threat": 18.45,
        "impact": 4.0,
        "progressor": 66.88,
        "off_ball": 45.5,
        "defensive": 5.95,
        "physical": 17.14
      },
      "progression_benchmark": {
        "score": 32.55,
        "quality": "strong",
        "support_actions": 6.0,
        "pass_only_line_break_volume": false
      },
      "hidden_gem_profile": {
        "eligible": true,
        "profile": "progression_engine",
        "score": 32.55
      },
      "score_components": [
        {
          "metric": "line_breaks_completed",
          "value": 31,
          "weight": 2.0,
          "contribution": 62.0
        },
        {
          "metric": "ball_progressions",
          "value": 2,
          "weight": 1.0,
          "contribution": 2.0
        },
        {
          "metric": "passes_completed",
          "value": 94,
          "weight": 0.02,
          "contribution": 1.88
        },
        {
          "metric": "take_ons",
          "value": 1,
          "weight": 0.5,
          "contribution": 0.5
        },
        {
          "metric": "step_ins",
          "value": 1,
          "weight": 0.5,
          "contribution": 0.5
        }
      ],
      "evidence_chips": {
        "en": [
          "goal scorer",
          "repeated line breaks",
          "found again and again"
        ],
        "zh": [
          "取得进球",
          "持续打穿防线",
          "持续接应"
        ]
      }
    },
    {
      "award_type": "hidden_gem",
      "award_label": {
        "en": "Hidden Gem",
        "zh": "隐藏亮点"
      },
      "rank": 1,
      "match_key": "FIFA-2026-M28-MEX-KOR",
      "match_no": 28,
      "player_no": 3,
      "player_name": "LEE Gihyuk",
      "team": "Korea Republic",
      "opponent": "Mexico",
      "home_score": 1,
      "away_score": 0,
      "team_final_goals": 0,
      "opponent_final_goals": 1,
      "position": "MF",
      "score": 32.9,
      "primary_score": "defensive",
      "role_scores": {
        "attacking_threat": 2.6,
        "impact": 0.0,
        "progressor": 31.0,
        "off_ball": 15.4,
        "defensive": 32.85,
        "physical": 16.49
      },
      "progression_benchmark": {
        "score": 16.3,
        "quality": "thin",
        "support_actions": 2.0,
        "pass_only_line_break_volume": false
      },
      "hidden_gem_profile": {
        "eligible": true,
        "profile": "defensive_resistance",
        "score": 50.85
      },
      "score_components": [
        {
          "metric": "possession_regains",
          "value": 9,
          "weight": 1.3,
          "contribution": 11.7
        },
        {
          "metric": "possession_interrupted",
          "value": 7,
          "weight": 1.0,
          "contribution": 7.0
        },
        {
          "metric": "interceptions",
          "value": 3,
          "weight": 1.5,
          "contribution": 4.5
        },
        {
          "metric": "clearances",
          "value": 7,
          "weight": 0.5,
          "contribution": 3.5
        },
        {
          "metric": "tackles_won",
          "value": 2,
          "weight": 1.5,
          "contribution": 3.0
        },
        {
          "metric": "blocks",
          "value": 2,
          "weight": 1.0,
          "contribution": 2.0
        }
      ],
      "evidence_chips": {
        "en": [
          "ball-winning profile"
        ],
        "zh": [
          "夺回球权能力突出"
        ]
      }
    }
  ],
  "selection_review": {
    "status": "publishable",
    "alerts": [
      {
        "level": "info",
        "code": "same_team_multiple_picks",
        "message": "Multiple picks can still come from one team when roles are clearly distinct.",
        "teams": [
          {
            "team": "Switzerland",
            "count": 2
          }
        ]
      }
    ],
    "iterations": [
      {
        "iteration": 1,
        "status": "needs_adjustment",
        "alerts": [
          {
            "level": "high",
            "code": "defensive_pick_from_heavy_loss",
            "message": "Nikola KATIC has the top defensive score, but Bosnia and Herzegovina conceded 4 in a heavy loss.",
            "player_name": "Nikola KATIC",
            "team": "Bosnia and Herzegovina",
            "replacement_candidate": "LEE Gihyuk"
          },
          {
            "level": "high",
            "code": "hidden_gem_duplicates_existing_team",
            "message": "Oswin APPOLLIS is a strong hidden-gem profile, but South Africa already has another pick and LEE Gihyuk gives the slate a distinct match angle.",
            "player_name": "Oswin APPOLLIS",
            "team": "South Africa",
            "replacement_candidate": "LEE Gihyuk"
          },
          {
            "level": "info",
            "code": "same_team_multiple_picks",
            "message": "Multiple picks can still come from one team when roles are clearly distinct.",
            "teams": [
              {
                "team": "South Africa",
                "count": 2
              },
              {
                "team": "Switzerland",
                "count": 2
              }
            ]
          }
        ],
        "choice_names": [
          "Jonathan DAVID",
          "Teboho MOKOENA",
          "Johan MANZAMBI",
          "Luis ROMO",
          "Granit XHAKA",
          "Oswin APPOLLIS",
          "Nikola KATIC"
        ]
      },
      {
        "iteration": 2,
        "status": "publishable",
        "alerts": [
          {
            "level": "info",
            "code": "same_team_multiple_picks",
            "message": "Multiple picks can still come from one team when roles are clearly distinct.",
            "teams": [
              {
                "team": "Switzerland",
                "count": 2
              }
            ]
          }
        ],
        "choice_names": [
          "Jonathan DAVID",
          "Teboho MOKOENA",
          "Johan MANZAMBI",
          "Luis ROMO",
          "Granit XHAKA",
          "LEE Gihyuk"
        ]
      }
    ]
  },
  "audit": []
}
